plover_vipe/__init__.py
plover_vipe/system.py
plover_vipe/dictionaries/vipe_commands.json
plover_vipe/dictionaries/vipe_main.json
plover_vipe-1.0.2.dist-info/LICENSE
plover_vipe-1.0.2.dist-info/METADATA
plover_vipe-1.0.2.dist-info/WHEEL
plover_vipe-1.0.2.dist-info/entry_points.txt
plover_vipe-1.0.2.dist-info/top_level.txt
plover_vipe-1.0.2.dist-info/zip-safe
plover_vipe-1.0.2.dist-info/RECORD
